exception_handler_plus/__init__.py
exception_handler_plus/exception_handler.py
exception_handler_plus/read_env.py
exception_handler_plus-0.1.0.dist-info/LICENSE
exception_handler_plus-0.1.0.dist-info/METADATA
exception_handler_plus-0.1.0.dist-info/WHEEL
exception_handler_plus-0.1.0.dist-info/top_level.txt
exception_handler_plus-0.1.0.dist-info/RECORD
