Metadata-Version: 2.1
Name: exception-handler-plus
Version: 0.1.0
Summary: Simple Exception Handler Decorator
Home-page: 
Author: Sergei Sazonov
Author-email: sspytdev@gmail.com
License: MIT
Classifier: Intended Audience :: Developers
Classifier: License :: OSI Approved :: MIT License
Classifier: Programming Language :: Python
Classifier: Programming Language :: Python :: 3
Classifier: Programming Language :: Python :: 3.8
Classifier: Programming Language :: Python :: 3.9
Classifier: Programming Language :: Python :: 3.10
Classifier: Programming Language :: Python :: 3.11
Classifier: Operating System :: OS Independent
License-File: LICENSE
